Metadata-Version: 2.4
Name: sl-suite2p
Version: 1.0.0
Summary: Modified suite2p implementation refactored to work with Sun (NeuroAI) lab's data processing pipeline.
Project-URL: Homepage, https://github.com/Sun-Lab-NBB/suite2p
Project-URL: Documentation, https://suite2p.readthedocs.io/en/latest/
Author: Marius Pachitariu, Carsen Stringer
Author-email: Kushaan Gupta <kg574@cornell.edu>, Ivan Kondratyev <ik278@cornell.edu>
Maintainer-email: Ivan Kondratyev <ik278@cornell.edu>
License:                     GNU GENERAL PUBLIC LICENSE
License-File: LICENSE
Keywords: mesoscope,suite2p,sunlab
Classifier: Development Status :: 5 - Production/Stable
Classifier: Intended Audience :: Developers
Classifier: License :: OSI Approved :: GNU General Public License v3 or later (GPLv3+)
Classifier: Operating System :: OS Independent
Classifier: Programming Language :: Python :: 3.11
Classifier: Programming Language :: Python :: 3.12
Classifier: Programming Language :: Python :: 3.13
Requires-Python: >=3.11
Requires-Dist: cellpose<4,>=3
Requires-Dist: dcimg<1,>=0
Requires-Dist: h5py<4,>=3
Requires-Dist: imagecodecs<2026,>=2025
Requires-Dist: matplotlib<4,>=3
Requires-Dist: natsort<9,>=8
Requires-Dist: nd2<1,>=0
Requires-Dist: numba<1,>=0.57
Requires-Dist: numpy<3,>=2
Requires-Dist: opencv-python-headless<5,>=4
Requires-Dist: paramiko<4,>=3.5.1
Requires-Dist: pynwb<4,>=3
Requires-Dist: pyqt5<6,>=5
Requires-Dist: pyqtgraph<1,>=0
Requires-Dist: qtpy<3,>=2
Requires-Dist: rastermap<2,>=1
Requires-Dist: sbxreader<1,>=0
Requires-Dist: scanimage-tiff-reader<2,>=1.4.1
Requires-Dist: scikit-learn<2,>=1
Requires-Dist: scipy<2,>=1.9
Requires-Dist: tifffile<2026,>=2025
Requires-Dist: xmltodict<1,>=0
Provides-Extra: conda
Requires-Dist: grayskull<3,>=2; extra == 'conda'
Requires-Dist: hatchling<2,>=1; extra == 'conda'
Requires-Dist: mypy<2,>=1; extra == 'conda'
Requires-Dist: ruff<1,>=0; extra == 'conda'
Requires-Dist: scipy-stubs<2,>=1; extra == 'conda'
Requires-Dist: twine<7,>=6; extra == 'conda'
Provides-Extra: condarun
Requires-Dist: h5py<4,>=3; extra == 'condarun'
Requires-Dist: matplotlib<4,>=3; extra == 'condarun'
Requires-Dist: natsort<9,>=8; extra == 'condarun'
Requires-Dist: nd2<1,>=0; extra == 'condarun'
Requires-Dist: numba<1,>=0.57; extra == 'condarun'
Requires-Dist: numpy<3,>=2; extra == 'condarun'
Requires-Dist: paramiko<4,>=3.5.1; extra == 'condarun'
Requires-Dist: pynwb<4,>=3; extra == 'condarun'
Requires-Dist: pyqtgraph<1,>=0; extra == 'condarun'
Requires-Dist: qtpy<3,>=2; extra == 'condarun'
Requires-Dist: scikit-learn<2,>=1; extra == 'condarun'
Requires-Dist: scipy<2,>=1.9; extra == 'condarun'
Requires-Dist: tifffile<2026,>=2025; extra == 'condarun'
Requires-Dist: xmltodict<1,>=0; extra == 'condarun'
Provides-Extra: dev
Requires-Dist: ataraxis-automation<5,>=4; extra == 'dev'
Requires-Dist: build<2,>=1; extra == 'dev'
Requires-Dist: grayskull<3,>=2; extra == 'dev'
Requires-Dist: hatchling<2,>=1; extra == 'dev'
Requires-Dist: mypy<2,>=1; extra == 'dev'
Requires-Dist: ruff<1,>=0; extra == 'dev'
Requires-Dist: scipy-stubs<2,>=1; extra == 'dev'
Requires-Dist: tox-uv<2,>=1; extra == 'dev'
Requires-Dist: tox<5,>=4; extra == 'dev'
Requires-Dist: twine<7,>=6; extra == 'dev'
Requires-Dist: uv<1,>=0; extra == 'dev'
Provides-Extra: noconda
Requires-Dist: ataraxis-automation<5,>=4; extra == 'noconda'
Requires-Dist: build<2,>=1; extra == 'noconda'
Requires-Dist: tox-uv<2,>=1; extra == 'noconda'
Requires-Dist: tox<5,>=4; extra == 'noconda'
Requires-Dist: uv<1,>=0; extra == 'noconda'
